thinkrf
