Metadata-Version: 1.0
Name: thinkrf
Version: 0.2.1
Summary: ThinkRF Python Device API
Home-page: https://github.com/thinkrf/python-thinkrf
Author: ThinkRF Corporation
Author-email: support@thinkrf.com
License: BSD
Platform: UNKNOWN
